

{
    "aboutUs": {
        "title": "关于我们",
        "children":[
                {
                    "title":"平台简介",
                    "path":"/about?TypeId=gywm&ID=oins2017040000000002"
                },
                {
                    "title":"公司简介",
                    "path":"/about?TypeId=gywm&ID=oins2017040000000003"
                }
            ]
        },
    "support": {
        "title":"服务与支持",
        "children":[
            {
                "title":"合作平台",
                "path":"/Business"
            },
            {
                "title":"在线支持",
                "path":"/about?TypeId=fwzc&ID=oins2017040000000007"
            },
            {
                "title":"联系我们",
                "path":"/about?TypeId=fwzc&ID=oins2017040000000008"
            },
            {
                "title":"平台服务说明",
                "path":"/platForm/PlatformExplain"
            }
        ]
    },
    "siteMap":{
        "title":"站点地图",
        "children":[
            {
                "title":"首页",
                "path":"/",
                "children":[
                    {
                        "title":"市场动态",
                        "path":"/information/IndustryList?TypeId=scdt"
                    },
                    {
                        "title":"招标资讯",
                        "path":"/information/IndustryList?TypeId=zbzx"
                    }
                ]
            },
            {
                "title":"招投标广场",
                "path":"/tenderSquare",
                "children":[
                    {
                        "title":"招标公告",
                        "hot":true,
                        "path":"/tenderSquare/tenderNotice"
                    },
                    {
                        "title":"变更公告",
                        "path":"/tenderSquare/changeNotice"
                    },
                    {
                        "title":"中标公告",
                        "path":"/tenderSquare/bidNotice"
                    }
                ]
            },
            {
                "title":"项目频道",
                "path":"/ProjectChannel",
                "children":[
                    {
                        "title":"VIP项目",
                        "hot":true,
                        "path":"/ProjectChannel/vipPro"
                    },
                    {
                        "title":"拟建项目",
                        "path":"/ProjectChannel/planPro"
                    },
                    {
                        "title":"在建项目",
                        "path":"/ProjectChannel/underPro"
                    },
                    {
                        "title":"委托项目",
                        "path":"/ProjectChannel/entrustPro"
                    }
                ]
            },
            {
                "title":"资讯",
                "path":"/information",
                "children":[
                    {
                        "title":"今日热点",
                        "hot":true,
                        "path":"/information/IndustryList?TypeId=jrrd"
                    },
                    {
                        "title":"热点专题",
                        "hot":true,
                        "path":"/information/IndustryList?TypeId=rdzt"
                    },
                    {
                        "title":"政策法规",
                        "path":"/information/IndustryList?TypeId=zcfg"
                    },
                    {
                        "title":"最新行业资讯",
                        "path":"/information/IndustryList?TypeId=hyzx"
                    }
                ]
            },
            {
                "title":"其他",
                "children":[
                    {
                        "title":"产品供应",
                        "path":"/productSupply"
                    },
                    {
                        "title":"采购专场",
                        "path":"/purchase"
                    },
                    {
                        "title":"行业展会",
                        "path":"/exhibition"
                    },
                    {
                        "title":"材料价格",
                        "path":"/price"
                    },
                    {
                        "title":"交易费用",
                        "path":"/Transaction"
                    },
                    {
                        "title":"企业平台",
                        "path":"/platForm"
                    }
                ]
            }
        ]
    }
}